proteobench/__init__.py
proteobench/exceptions.py
proteobench/datapoint/quant_datapoint.py
proteobench/github/gh.py
proteobench/io/__init__.py
proteobench/io/data/.gitkeep
proteobench/io/params/README.md
proteobench/io/params/__init__.py
proteobench/io/params/alphadia.py
proteobench/io/params/alphapept.py
proteobench/io/params/diann.py
proteobench/io/params/fragger.py
proteobench/io/params/i2masschroq.py
proteobench/io/params/maxdia.py
proteobench/io/params/maxquant.py
proteobench/io/params/metamorpheus.py
proteobench/io/params/msaid.py
proteobench/io/params/msangel.py
proteobench/io/params/peaks.py
proteobench/io/params/proline.py
proteobench/io/params/quantms.py
proteobench/io/params/sage.py
proteobench/io/params/spectronaut.py
proteobench/io/params/wombat.py
proteobench/io/params/json/Quant/README.md
proteobench/io/params/json/Quant/quant_lfq_DDA_ion.json
proteobench/io/params/json/Quant/quant_lfq_DDA_peptidoform.json
proteobench/io/params/json/Quant/quant_lfq_DIA_ion.json
proteobench/io/params/json/Quant/quant_lfq_DIA_peptidoform.json
proteobench/io/parsing/README.md
proteobench/io/parsing/__init__.py
proteobench/io/parsing/parse_ion.py
proteobench/io/parsing/parse_peptidoform.py
proteobench/io/parsing/parse_settings.py
proteobench/io/parsing/utils.py
proteobench/io/parsing/io_parse_settings/README.md
proteobench/io/parsing/io_parse_settings/mapper.csv
proteobench/io/parsing/io_parse_settings/parse_settings_files.toml
proteobench/io/parsing/io_parse_settings/Quant/lfq/DDA/ion/Astral/module_settings.toml
proteobench/io/parsing/io_parse_settings/Quant/lfq/DDA/ion/Astral/parse_settings_alphapept.toml
proteobench/io/parsing/io_parse_settings/Quant/lfq/DDA/ion/Astral/parse_settings_custom.toml
proteobench/io/parsing/io_parse_settings/Quant/lfq/DDA/ion/Astral/parse_settings_fragpipe.toml
proteobench/io/parsing/io_parse_settings/Quant/lfq/DDA/ion/Astral/parse_settings_i2massChroQ.toml
proteobench-0.10.2.dist-info/licenses/LICENSE
proteobench-0.10.2.dist-info/METADATA
proteobench-0.10.2.dist-info/WHEEL
proteobench-0.10.2.dist-info/top_level.txt
proteobench-0.10.2.dist-info/RECORD
