Metadata-Version: 2.4
Name: proteobench
Version: 0.10.2
Summary: ProteoBench compares the outputs of mass spectrometry-based proteomics data analysis pipelines
Author-email: Robbin Bouwmeester <robbin.bouwmeester@ugent.be>, Henry Webel <heweb@dtu.dk>, Witold Wolski <witold.wolski@fgcz.uzh.ch>
License:                                  Apache License
Project-URL: Bug Tracker, https://github.com/ProteoBench/ProteoBench/issues/
Project-URL: Homepage, https://github.com/ProteoBench
Keywords: proteomics,peptides,retention time,mass spectrometry
Classifier: Intended Audience :: Science/Research
Classifier: License :: OSI Approved :: Apache Software License
Classifier: Operating System :: OS Independent
Classifier: Programming Language :: Python :: 3
Classifier: Topic :: Scientific/Engineering :: Bio-Informatics
Classifier: Development Status :: 4 - Beta
Requires-Python: >=3.11
License-File: LICENSE
Requires-Dist: pandas[excel]
Requires-Dist: openpyxl
Requires-Dist: numpy>1.24.4
Requires-Dist: plotly>=6.0.0
Requires-Dist: upsetplot
Requires-Dist: seaborn
Requires-Dist: streamlit>=1.31
Requires-Dist: streamlit-aggrid>=1.1.7
Requires-Dist: streamlit_extras
Requires-Dist: streamlit-plotly-events
Requires-Dist: scipy
Requires-Dist: matplotlib
Requires-Dist: toml
Requires-Dist: PyGithub
Requires-Dist: GitPython
Requires-Dist: psm-utils
Requires-Dist: pmultiqc>=0.0.33
Provides-Extra: dev
Requires-Dist: black~=23.0; extra == "dev"
Requires-Dist: jupyterlab; extra == "dev"
Requires-Dist: ipywidgets; extra == "dev"
Requires-Dist: notebook; extra == "dev"
Requires-Dist: tqdm; extra == "dev"
Requires-Dist: wget; extra == "dev"
Requires-Dist: nox; extra == "dev"
Requires-Dist: pytest; extra == "dev"
Provides-Extra: docs
Requires-Dist: sphinx; extra == "docs"
Requires-Dist: sphinx-design; extra == "docs"
Requires-Dist: sphinx-rtd-theme; extra == "docs"
Requires-Dist: sphinx-autobuild; extra == "docs"
Requires-Dist: myst-parser>=0.3.0; extra == "docs"
Requires-Dist: pydata-sphinx-theme; extra == "docs"
Requires-Dist: sphinx_new_tab_link; extra == "docs"
Requires-Dist: sphinx_copybutton; extra == "docs"
Provides-Extra: web
Requires-Dist: streamlit>1.27; extra == "web"
Requires-Dist: scipy; extra == "web"
Dynamic: license-file
